{
  "ts": "2026-03-14T06:55:38.718109+00:00",
  "mode": "fetch",
  "ok": true,
  "base_url": "http://127.0.0.1:8000",
  "use_mock": true,
  "report_id": "auction-2026-03-14-e7b6884222",
  "trade_date": "2026-03-14",
  "summary_data": {
    "top_gainers": [
      {
        "code": "SZ300308",
        "name": "中际旭创",
        "change_pct": 4.91,
        "turnover": 320000000.0
      },
      {
        "code": "SZ002371",
        "name": "北方华创",
        "change_pct": 3.88,
        "turnover": 260000000.0
      }
    ],
    "top_losers": [
      {
        "code": "SH600519",
        "name": "贵州茅台",
        "change_pct": -1.22,
        "turnover": 140000000.0
      }
    ],
    "turnover_top": [
      {
        "code": "SZ300750",
        "name": "宁德时代",
        "change_pct": 1.09,
        "turnover": 480000000.0
      },
      {
        "code": "SH601318",
        "name": "中国平安",
        "change_pct": 0.72,
        "turnover": 370000000.0
      }
    ],
    "limit_up_candidates": [
      "机器人",
      "算力服务"
    ],
    "auction_sentiment": 58.5
  },
  "warnings": [],
  "auction_api_response": {
    "ok": true,
    "data": {
      "report_id": "auction-2026-03-14-e7b6884222",
      "report_type": "auction",
      "trade_date": "2026-03-14",
      "generated_at": "2026-03-14T14:55:38.715194+08:00",
      "summary_data": {
        "top_gainers": [
          {
            "code": "SZ300308",
            "name": "中际旭创",
            "change_pct": 4.91,
            "turnover": 320000000.0
          },
          {
            "code": "SZ002371",
            "name": "北方华创",
            "change_pct": 3.88,
            "turnover": 260000000.0
          }
        ],
        "top_losers": [
          {
            "code": "SH600519",
            "name": "贵州茅台",
            "change_pct": -1.22,
            "turnover": 140000000.0
          }
        ],
        "turnover_top": [
          {
            "code": "SZ300750",
            "name": "宁德时代",
            "change_pct": 1.09,
            "turnover": 480000000.0
          },
          {
            "code": "SH601318",
            "name": "中国平安",
            "change_pct": 0.72,
            "turnover": 370000000.0
          }
        ],
        "limit_up_candidates": [
          "机器人",
          "算力服务"
        ],
        "auction_sentiment": 58.5
      },
      "raw_data": {
        "top_gainers": [
          {
            "code": "300308",
            "name": "中际旭创",
            "change_pct": 4.91,
            "turnover": 320000000.0
          },
          {
            "code": "002371",
            "name": "北方华创",
            "change_pct": 3.88,
            "turnover": 260000000.0
          }
        ],
        "top_losers": [
          {
            "code": "600519",
            "name": "贵州茅台",
            "change_pct": -1.22,
            "turnover": 140000000.0
          }
        ],
        "turnover_top": [
          {
            "code": "300750",
            "name": "宁德时代",
            "change_pct": 1.09,
            "turnover": 480000000.0
          },
          {
            "code": "601318",
            "name": "中国平安",
            "change_pct": 0.72,
            "turnover": 370000000.0
          }
        ],
        "limit_up_candidates": [
          "机器人",
          "算力服务"
        ],
        "auction_sentiment": 58.5
      },
      "warnings": [],
      "status": "SUCCESS",
      "source": "mock"
    },
    "error": null
  }
}